csv_magic_htwk/__init__.py
csv_magic_htwk-1.0.dist-info/METADATA
csv_magic_htwk-1.0.dist-info/WHEEL
csv_magic_htwk-1.0.dist-info/licenses/LICENSE
csv_magic_htwk-1.0.dist-info/RECORD
