Metadata-Version: 2.4
Name: csv_magic_htwk
Version: 1.0
Summary: Jupyter Magic zur einfachen Darstellung von CSV-Daten
Author-email: Andreas Thor <andreas.thor@htwk-leipzig.de>
License-Expression: MIT
License-File: LICENSE
Classifier: License :: OSI Approved :: MIT License
Classifier: Operating System :: OS Independent
Classifier: Programming Language :: Python :: 3
Requires-Python: >=3.9
Requires-Dist: pandas>=2.2.1
